Classfile /C:/Users/Karans/Dropbox/CSD/Kurslar/Java-Nov-2021/src/Sample/out/production/Sample/org/csystem/app/Sample.class
  Last modified Jul 13, 2022; size 792 bytes
  SHA-256 checksum acb342c661a8f187c66bd0acaf6eb94a4da21d9490bb00950738f6bc0b4cdf46
  Compiled from "App.java"
class org.csystem.app.Sample
  minor version: 0
  major version: 61
  flags: (0x0020) ACC_SUPER
  this_class: #8                          // org/csystem/app/Sample
  super_class: #2                         // java/lang/Object
  interfaces: 0, fields: 1, methods: 5, attributes: 1
Constant pool:
   #1 = Methodref          #2.#3          // java/lang/Object."<init>":()V
   #2 = Class              #4             // java/lang/Object
   #3 = NameAndType        #5:#6          // "<init>":()V
   #4 = Utf8               java/lang/Object
   #5 = Utf8               <init>
   #6 = Utf8               ()V
   #7 = Fieldref           #8.#9          // org/csystem/app/Sample.m_x:I
   #8 = Class              #10            // org/csystem/app/Sample
   #9 = NameAndType        #11:#12        // m_x:I
  #10 = Utf8               org/csystem/app/Sample
  #11 = Utf8               m_x
  #12 = Utf8               I
  #13 = Fieldref           #14.#15        // java/lang/System.out:Ljava/io/PrintStream;
  #14 = Class              #16            // java/lang/System
  #15 = NameAndType        #17:#18        // out:Ljava/io/PrintStream;
  #16 = Utf8               java/lang/System
  #17 = Utf8               out
  #18 = Utf8               Ljava/io/PrintStream;
  #19 = Methodref          #20.#21        // java/io/PrintStream.println:(I)V
  #20 = Class              #22            // java/io/PrintStream
  #21 = NameAndType        #23:#24        // println:(I)V
  #22 = Utf8               java/io/PrintStream
  #23 = Utf8               println
  #24 = Utf8               (I)V
  #25 = Utf8               Code
  #26 = Utf8               LineNumberTable
  #27 = Utf8               LocalVariableTable
  #28 = Utf8               this
  #29 = Utf8               Lorg/csystem/app/Sample;
  #30 = Utf8               setX
  #31 = Utf8               x
  #32 = Utf8               (Lorg/csystem/app/Sample;I)V
  #33 = Utf8               s
  #34 = Utf8               print
  #35 = Utf8               (Lorg/csystem/app/Sample;)V
  #36 = Utf8               SourceFile
  #37 = Utf8               App.java
{
  org.csystem.app.Sample();
    descriptor: ()V
    flags: (0x0000)
    Code:
      stack=1, locals=1, args_size=1
         0: aload_0
         1: invokespecial #1                  // Method java/lang/Object."<init>":()V
         4: return
      LineNumberTable:
        line 36: 0
      LocalVariableTable:
        Start  Length  Slot  Name   Signature
            0       5     0  this   Lorg/csystem/app/Sample;

  public void setX(int);
    descriptor: (I)V
    flags: (0x0001) ACC_PUBLIC
    Code:
      stack=2, locals=2, args_size=2
         0: aload_0
         1: iload_1
         2: putfield      #7                  // Field m_x:I
         5: return
      LineNumberTable:
        line 42: 0
        line 43: 5
      LocalVariableTable:
        Start  Length  Slot  Name   Signature
            0       6     0  this   Lorg/csystem/app/Sample;
            0       6     1     x   I

  public static void setX(org.csystem.app.Sample, int);
    descriptor: (Lorg/csystem/app/Sample;I)V
    flags: (0x0009) ACC_PUBLIC, ACC_STATIC
    Code:
      stack=2, locals=2, args_size=2
         0: aload_0
         1: iload_1
         2: putfield      #7                  // Field m_x:I
         5: return
      LineNumberTable:
        line 48: 0
        line 49: 5
      LocalVariableTable:
        Start  Length  Slot  Name   Signature
            0       6     0     s   Lorg/csystem/app/Sample;
            0       6     1     x   I

  public void print();
    descriptor: ()V
    flags: (0x0001) ACC_PUBLIC
    Code:
      stack=2, locals=1, args_size=1
         0: getstatic     #13                 // Field java/lang/System.out:Ljava/io/PrintStream;
         3: aload_0
         4: getfield      #7                  // Field m_x:I
         7: invokevirtual #19                 // Method java/io/PrintStream.println:(I)V
        10: return
      LineNumberTable:
        line 53: 0
        line 54: 10
      LocalVariableTable:
        Start  Length  Slot  Name   Signature
            0      11     0  this   Lorg/csystem/app/Sample;

  public static void print(org.csystem.app.Sample);
    descriptor: (Lorg/csystem/app/Sample;)V
    flags: (0x0009) ACC_PUBLIC, ACC_STATIC
    Code:
      stack=2, locals=1, args_size=1
         0: getstatic     #13                 // Field java/lang/System.out:Ljava/io/PrintStream;
         3: aload_0
         4: getfield      #7                  // Field m_x:I
         7: invokevirtual #19                 // Method java/io/PrintStream.println:(I)V
        10: return
      LineNumberTable:
        line 59: 0
        line 60: 10
      LocalVariableTable:
        Start  Length  Slot  Name   Signature
            0      11     0     s   Lorg/csystem/app/Sample;
}
SourceFile: "App.java"
Classfile /C:/Users/Karans/Dropbox/CSD/Kurslar/Java-Nov-2021/src/Sample/out/production/Sample/org/csystem/app/App.class
  Last modified Jul 13, 2022; size 629 bytes
  SHA-256 checksum 091e8750ecb507c1551dcba7c1a8264bb7cf06711d61c097cb4780d1b930558b
  Compiled from "App.java"
class org.csystem.app.App
  minor version: 0
  major version: 61
  flags: (0x0020) ACC_SUPER
  this_class: #23                         // org/csystem/app/App
  super_class: #2                         // java/lang/Object
  interfaces: 0, fields: 0, methods: 2, attributes: 1
Constant pool:
   #1 = Methodref          #2.#3          // java/lang/Object."<init>":()V
   #2 = Class              #4             // java/lang/Object
   #3 = NameAndType        #5:#6          // "<init>":()V
   #4 = Utf8               java/lang/Object
   #5 = Utf8               <init>
   #6 = Utf8               ()V
   #7 = Class              #8             // org/csystem/app/Sample
   #8 = Utf8               org/csystem/app/Sample
   #9 = Methodref          #7.#3          // org/csystem/app/Sample."<init>":()V
  #10 = Methodref          #7.#11         // org/csystem/app/Sample.setX:(I)V
  #11 = NameAndType        #12:#13        // setX:(I)V
  #12 = Utf8               setX
  #13 = Utf8               (I)V
  #14 = Methodref          #7.#15         // org/csystem/app/Sample.setX:(Lorg/csystem/app/Sample;I)V
  #15 = NameAndType        #12:#16        // setX:(Lorg/csystem/app/Sample;I)V
  #16 = Utf8               (Lorg/csystem/app/Sample;I)V
  #17 = Methodref          #7.#18         // org/csystem/app/Sample.print:()V
  #18 = NameAndType        #19:#6         // print:()V
  #19 = Utf8               print
  #20 = Methodref          #7.#21         // org/csystem/app/Sample.print:(Lorg/csystem/app/Sample;)V
  #21 = NameAndType        #19:#22        // print:(Lorg/csystem/app/Sample;)V
  #22 = Utf8               (Lorg/csystem/app/Sample;)V
  #23 = Class              #24            // org/csystem/app/App
  #24 = Utf8               org/csystem/app/App
  #25 = Utf8               Code
  #26 = Utf8               LineNumberTable
  #27 = Utf8               LocalVariableTable
  #28 = Utf8               this
  #29 = Utf8               Lorg/csystem/app/App;
  #30 = Utf8               main
  #31 = Utf8               ([Ljava/lang/String;)V
  #32 = Utf8               args
  #33 = Utf8               [Ljava/lang/String;
  #34 = Utf8               s
  #35 = Utf8               Lorg/csystem/app/Sample;
  #36 = Utf8               SourceFile
  #37 = Utf8               App.java
{
  org.csystem.app.App();
    descriptor: ()V
    flags: (0x0000)
    Code:
      stack=1, locals=1, args_size=1
         0: aload_0
         1: invokespecial #1                  // Method java/lang/Object."<init>":()V
         4: return
      LineNumberTable:
        line 19: 0
      LocalVariableTable:
        Start  Length  Slot  Name   Signature
            0       5     0  this   Lorg/csystem/app/App;

  public static void main(java.lang.String[]);
    descriptor: ([Ljava/lang/String;)V
    flags: (0x0009) ACC_PUBLIC, ACC_STATIC
    Code:
      stack=2, locals=2, args_size=1
         0: new           #7                  // class org/csystem/app/Sample
         3: dup
         4: invokespecial #9                  // Method org/csystem/app/Sample."<init>":()V
         7: astore_1
         8: aload_1
         9: bipush        10
        11: invokevirtual #10                 // Method org/csystem/app/Sample.setX:(I)V
        14: aload_1
        15: bipush        10
        17: invokestatic  #14                 // Method org/csystem/app/Sample.setX:(Lorg/csystem/app/Sample;I)V
        20: aload_1
        21: invokevirtual #17                 // Method org/csystem/app/Sample.print:()V
        24: aload_1
        25: invokestatic  #20                 // Method org/csystem/app/Sample.print:(Lorg/csystem/app/Sample;)V
        28: return
      LineNumberTable:
        line 22: 0
        line 24: 8
        line 27: 14
        line 29: 20
        line 32: 24
        line 33: 28
      LocalVariableTable:
        Start  Length  Slot  Name   Signature
            0      29     0  args   [Ljava/lang/String;
            8      21     1     s   Lorg/csystem/app/Sample;
}
SourceFile: "App.java"
